{
    "remotePath": "./",
    "host": "members.chello.at",
    "username": "aschweitzer",
    "password": "Sunny9376!upc",
    "port": 21,
    "secure": false,
    "protocol": "ftp",
    "uploadOnSave": false,
    "passive": false,
    "debug": false,
    "privateKeyPath": null,
    "passphrase": null,
    "agent": null,
    "allow": [],
    "ignore": [
        "\\.vscode",
        "\\.git",
        "\\.DS_Store"
    ],
    "generatedFiles": {
        "extensionsToInclude": [
            ""
        ],
        "path": ""
    }
}